jthon/__init__.py
jthon/errors.py
jthon/found.py
jthon/jthon.py
jthon-1.0.6.dist-info/LICENSE.txt
jthon-1.0.6.dist-info/METADATA
jthon-1.0.6.dist-info/WHEEL
jthon-1.0.6.dist-info/RECORD
